pubsub_ncs/__init__.py
pubsub_ncs/publisher.py
pubsub_ncs/pubsubbase.py
pubsub_ncs/subscriber.py
pubsub_ncs-1.0.0.dist-info/METADATA
pubsub_ncs-1.0.0.dist-info/WHEEL
pubsub_ncs-1.0.0.dist-info/top_level.txt
pubsub_ncs-1.0.0.dist-info/RECORD
